hfc/__init__.py
hfc/version.py
hfc/fabric/__init__.py
hfc/fabric/block_decoder.py
hfc/fabric/certificateAuthority.py
hfc/fabric/client.py
hfc/fabric/orderer.py
hfc/fabric/organization.py
hfc/fabric/peer.py
hfc/fabric/user.py
hfc/fabric/channel/__init__.py
hfc/fabric/channel/channel.py
hfc/fabric/channel/channel_configuration.py
hfc/fabric/channel/channel_eventhub.py
hfc/fabric/channel/instantiation.py
hfc/fabric/channel/invocation.py
hfc/fabric/config/__init__.py
hfc/fabric/config/default.py
hfc/fabric/msp/__init__.py
hfc/fabric/transaction/__init__.py
hfc/fabric/transaction/tx_context.py
hfc/fabric/transaction/tx_proposal_request.py
hfc/fabric_ca/__init__.py
hfc/fabric_ca/affiliationService.py
hfc/fabric_ca/caservice.py
hfc/fabric_ca/certificateService.py
hfc/fabric_ca/identityService.py
hfc/fabric_network/__init__.py
hfc/fabric_network/contract.py
hfc/fabric_network/couchdbwalletstore.py
hfc/fabric_network/gateway.py
hfc/fabric_network/inmemorywalletstore.py
hfc/fabric_network/network.py
hfc/fabric_network/wallet.py
hfc/protos/__init__.py
hfc/protos/utils.py
hfc/protos/common/__init__.py
hfc/protos/common/collection_pb2.py
hfc/protos/common/collection_pb2_grpc.py
hfc/protos/common/common_pb2.py
hfc/protos/common/common_pb2_grpc.py
hfc/protos/common/configtx_pb2.py
hfc/protos/common/configtx_pb2_grpc.py
hfc/protos/common/configuration_pb2.py
hfc/protos/common/configuration_pb2_grpc.py
hfc/protos/common/ledger_pb2.py
hfc/protos/common/ledger_pb2_grpc.py
hfc/protos/common/policies_pb2.py
hfc/protos/common/policies_pb2_grpc.py
hfc/protos/discovery/__init__.py
hfc/protos/discovery/protocol_pb2.py
hfc/protos/discovery/protocol_pb2_grpc.py
hfc/protos/gossip/__init__.py
hfc/protos/gossip/message_pb2.py
hfc/protos/gossip/message_pb2_grpc.py
hfc/protos/idemix/__init__.py
hfc/protos/idemix/idemix_pb2.py
hfc/protos/idemix/idemix_pb2_grpc.py
hfc/protos/ledger/__init__.py
hfc/protos/ledger/queryresult/__init__.py
hfc/protos/ledger/queryresult/kv_query_result_pb2.py
fabric_sdk_py-1.0.0.dist-info/LICENSE
fabric_sdk_py-1.0.0.dist-info/METADATA
fabric_sdk_py-1.0.0.dist-info/WHEEL
fabric_sdk_py-1.0.0.dist-info/top_level.txt
fabric_sdk_py-1.0.0.dist-info/RECORD
