Metadata-Version: 1.1
Name: fabric-sdk-py
Version: 1.0.0
Summary: Python SDK for Hyperledger Fabric.
Home-page: https://github.com/hyperledger/fabric-sdk-py/
Author: Hyperledger Community
Author-email: UNKNOWN
License: Apache License v2.0
Download-URL: https://github.com/hyperledger/fabric-sdk-py/
Keywords: Hyperledger Fabric,SDK
Platform: any
Classifier: Development Status :: 3 - Alpha
Classifier: Environment :: Other Environment
Classifier: Intended Audience :: Developers
Classifier: Operating System :: OS Independent
Classifier: Programming Language :: Python :: 3.6
Classifier: Topic :: Utilities
Classifier: License :: OSI Approved :: Apache Software License
